data/__init__.py
data/celestial_data.py
orbitarium/__init__.py
orbitarium/core.py
orbitarium-1.0.1.dist-info/LICENSE
orbitarium-1.0.1.dist-info/METADATA
orbitarium-1.0.1.dist-info/WHEEL
orbitarium-1.0.1.dist-info/top_level.txt
orbitarium-1.0.1.dist-info/RECORD
