Metadata-Version: 2.1
Name: orbitarium
Version: 1.0.1
Summary: A library to approximate positions of planets and moons in our Solar System.
Home-page: https://github.com/koell/orbitarium
Author: Fabian Köll
Author-email: Fabian Köll <koell.dev@gmail.com>
License: GPLv3
Project-URL: Homepage, https://github.com/koell/orbitarium
Project-URL: Issues, https://github.com/koell/orbitarium/issues
Classifier: Programming Language :: Python :: 3
Classifier: License :: OSI Approved :: GNU General Public License v3 (GPLv3)
Classifier: Operating System :: OS Independent
Requires-Python: >=3.8
License-File: LICENSE
